agents/__init__.py
agents/agents.py
api/__init__.py
api/api_app.py
api/routes.py
tasks/__init__.py
tasks/tasks.py
tools/__init__.py
tools/browser_tools.py
tools/custom_docling.py
tools/custom_scraping.py
tools/custom_tika.py
tools/custom_unstructured.py
tools/sample.py
tools/sample1.py
tools/sample2.py
utils/__init__.py
utils/logger.py
resume_ats-0.1.0.dist-info/METADATA
resume_ats-0.1.0.dist-info/WHEEL
resume_ats-0.1.0.dist-info/entry_points.txt
resume_ats-0.1.0.dist-info/top_level.txt
resume_ats-0.1.0.dist-info/RECORD
